pytest_sentry/__init__.py
pytest_sentry/client.py
pytest_sentry/consts.py
pytest_sentry/fixtures.py
pytest_sentry/helpers.py
pytest_sentry/hooks.py
pytest_sentry/integration.py
pytest_sentry-0.5.1.dist-info/licenses/LICENSE
pytest_sentry-0.5.1.dist-info/METADATA
pytest_sentry-0.5.1.dist-info/WHEEL
pytest_sentry-0.5.1.dist-info/entry_points.txt
pytest_sentry-0.5.1.dist-info/top_level.txt
pytest_sentry-0.5.1.dist-info/RECORD
