Metadata-Version: 2.4
Name: pytest_sentry
Version: 0.5.1
Summary: A pytest plugin to send testrun information to Sentry.io
Home-page: https://github.com/untitaker/pytest-sentry
Author: Markus Unterwaditzer
Author-email: markus@unterwaditzer.net
License: BSD-2-Clause
Classifier: License :: OSI Approved :: BSD License
License-File: LICENSE
Requires-Dist: pytest
Requires-Dist: sentry-sdk>=3.0.0a1
Requires-Dist: wrapt
Dynamic: license-file
